{"uid": 0, "input": "", "Character": {"Name": "煙緋(monaonlywins)", "Const": 6, "Level": 90, "Love": 10, "Costume": "", "Status": {"HP": 15208, "攻撃力": 1792, "防御力": 659, "元素熟知": 84, "会心率": 71.5, "会心ダメージ": 165.0, "元素チャージ効率": 125.3, "炎元素ダメージ": 85.6}, "Talent": {"通常": 10, "スキル": 13, "爆発": 13}, "Base": {"HP": 9352, "攻撃力": 848, "防御力": 587}}, "Weapon": {"name": "四風原典", "Level": 90, "totu": 1, "rarelity": 5, "BaseATK": 608, "Sub": {"name": "会心率", "value": 33.1}}, "Score": {"State": "攻撃パーセンテージ", "total": 147.6, "flower": 40.4, "wing": 25.2, "clock": 28.0, "cup": 20.2, "crown": 33.8},"Artifacts":{"flower": {"type": "燃え盛る炎の魔女", "Level": 20, "rarelity": 5, "main": {"option": "HP", "value": 4780}, "sub": [{"option": "会心ダメージ", "value": 11.7}, {"option": "元素熟知", "value": 19}, {"option": "攻撃パーセンテージ", "value": 16.3}, {"option": "会心率", "value": 6.2}]},"wing": {"type": "燃え盛る炎の魔女", "Level": 20, "rarelity": 5, "main": {"option": "攻撃力", "value": 311}, "sub": [{"option": "会心ダメージ", "value": 19.4}, {"option": "攻撃パーセンテージ", "value": 5.8}, {"option": "元素チャージ効率", "value": 4.5}, {"option": "元素熟知", "value": 65}]},"clock": {"type": "燃え盛る炎の魔女", "Level": 20, "rarelity": 5, "main": {"option": "攻撃パーセンテージ", "value": 46.6}, "sub": [{"option": "会心率", "value": 10.5}, {"option": "会心ダメージ", "value": 7}, {"option": "元素チャージ効率", "value": 10.4}, {"option": "防御力", "value": 35}]},"cup": {"type": "燃え盛る炎の魔女", "Level": 20, "rarelity": 5, "main": {"option": "炎元素ダメージ", "value": 46.6}, "sub": [{"option": "元素チャージ効率", "value": 10.4}, {"option": "会心率", "value": 2.7}, {"option": "HP", "value": 777}, {"option": "会心ダメージ", "value": 14.8}]},"crown": {"type": "金メッキの夢", "Level": 20, "rarelity": 5, "main": {"option": "会心ダメージ", "value": 62.2}, "sub": [{"option": "攻撃パーセンテージ", "value": 5.8}, {"option": "防御力", "value": 37}, {"option": "HP", "value": 299}, {"option": "会心率", "value": 14}]}},"元素": "炎"}