{"uid": 0, "input": "", "Character": {"Name": "久岐忍", "Const": 1, "Level": 83, "Love": 2, "Costume": "", "Status": {"HP": 21223, "攻撃力": 1111, "防御力": 918, "元素熟知": 872, "会心率": 21.3, "会心ダメージ": 81.9, "元素チャージ効率": 169.3, "雷元素ダメージ": 0}, "Talent": {"通常": 1, "スキル": 6, "爆発": 1}, "Base": {"HP": 11693, "攻撃力": 651, "防御力": 714}}, "Weapon": {"name": "鉄蜂の刺し", "Level": 80, "totu": 1, "rarelity": 4, "BaseATK": 449, "Sub": {"name": "元素熟知", "value": 151}}, "Score": {"State": "元素熟知", "total": 85.0, "flower": 31.5, "wing": 10.0, "clock": 23.3, "cup": 14, "crown": 6.2},"Artifacts":{"flower": {"type": "金メッキの夢", "Level": 20, "rarelity": 5, "main": {"option": "HP", "value": 4780}, "sub": [{"option": "会心率", "value": 10.5}, {"option": "HPパーセンテージ", "value": 5.3}, {"option": "元素熟知", "value": 42}, {"option": "元素チャージ効率", "value": 16.8}]},"wing": {"type": "金メッキの夢", "Level": 20, "rarelity": 5, "main": {"option": "攻撃力", "value": 311}, "sub": [{"option": "元素チャージ効率", "value": 21.4}, {"option": "防御力", "value": 16}, {"option": "HPパーセンテージ", "value": 9.3}, {"option": "元素熟知", "value": 40}]},"clock": {"type": "金メッキの夢", "Level": 20, "rarelity": 5, "main": {"option": "元素熟知", "value": 187}, "sub": [{"option": "会心ダメージ", "value": 11.7}, {"option": "元素チャージ効率", "value": 4.5}, {"option": "会心率", "value": 5.8}, {"option": "攻撃力", "value": 47}]},"cup": {"type": "旧貴族のしつけ", "Level": 20, "rarelity": 5, "main": {"option": "元素熟知", "value": 187}, "sub": [{"option": "会心ダメージ", "value": 14}, {"option": "HP", "value": 239}, {"option": "防御パーセンテージ", "value": 7.3}, {"option": "元素チャージ効率", "value": 20.7}]},"crown": {"type": "金メッキの夢", "Level": 20, "rarelity": 5, "main": {"option": "元素熟知", "value": 187}, "sub": [{"option": "元素チャージ効率", "value": 5.8}, {"option": "会心ダメージ", "value": 6.2}, {"option": "防御パーセンテージ", "value": 19}, {"option": "攻撃パーセンテージ", "value": 15.7}]}},"元素": "雷"}